
<annotation>
    <folder>images</folder>
    <filename>hard_hat_workers3901.png</filename>
    <size>
        <width>416</width>
        <height>415</height>
        <depth>3</depth>
    </size>
    <segmented>0</segmented>
    <object>
        <name>head</name>
        <pose>Unspecified</pose>
        <truncated>0</truncated>
        <occluded>0</occluded>
        <difficult>0</difficult>
        <bndbox>
            <xmin>56</xmin>
            <ymin>132</ymin>
            <xmax>85</xmax>
            <ymax>168</ymax>
        </bndbox>
    </object>
    <object>
        <name>head</name>
        <pose>Unspecified</pose>
        <truncated>0</truncated>
        <occluded>0</occluded>
        <difficult>0</difficult>
        <bndbox>
            <xmin>135</xmin>
            <ymin>133</ymin>
            <xmax>155</xmax>
            <ymax>163</ymax>
        </bndbox>
    </object>
    <object>
        <name>head</name>
        <pose>Unspecified</pose>
        <truncated>0</truncated>
        <occluded>0</occluded>
        <difficult>0</difficult>
        <bndbox>
            <xmin>175</xmin>
            <ymin>144</ymin>
            <xmax>194</xmax>
            <ymax>171</ymax>
        </bndbox>
    </object>
    <object>
        <name>head</name>
        <pose>Unspecified</pose>
        <truncated>0</truncated>
        <occluded>0</occluded>
        <difficult>0</difficult>
        <bndbox>
            <xmin>39</xmin>
            <ymin>146</ymin>
            <xmax>56</xmax>
            <ymax>171</ymax>
        </bndbox>
    </object>
    <object>
        <name>head</name>
        <pose>Unspecified</pose>
        <truncated>0</truncated>
        <occluded>0</occluded>
        <difficult>0</difficult>
        <bndbox>
            <xmin>119</xmin>
            <ymin>144</ymin>
            <xmax>134</xmax>
            <ymax>168</ymax>
        </bndbox>
    </object>
    <object>
        <name>head</name>
        <pose>Unspecified</pose>
        <truncated>0</truncated>
        <occluded>0</occluded>
        <difficult>0</difficult>
        <bndbox>
            <xmin>195</xmin>
            <ymin>149</ymin>
            <xmax>211</xmax>
            <ymax>170</ymax>
        </bndbox>
    </object>
    <object>
        <name>head</name>
        <pose>Unspecified</pose>
        <truncated>0</truncated>
        <occluded>0</occluded>
        <difficult>0</difficult>
        <bndbox>
            <xmin>218</xmin>
            <ymin>153</ymin>
            <xmax>233</xmax>
            <ymax>170</ymax>
        </bndbox>
    </object>
    <object>
        <name>head</name>
        <pose>Unspecified</pose>
        <truncated>0</truncated>
        <occluded>0</occluded>
        <difficult>0</difficult>
        <bndbox>
            <xmin>89</xmin>
            <ymin>144</ymin>
            <xmax>110</xmax>
            <ymax>167</ymax>
        </bndbox>
    </object>
    <object>
        <name>head</name>
        <pose>Unspecified</pose>
        <truncated>0</truncated>
        <occluded>0</occluded>
        <difficult>0</difficult>
        <bndbox>
            <xmin>2</xmin>
            <ymin>153</ymin>
            <xmax>20</xmax>
            <ymax>172</ymax>
        </bndbox>
    </object>
    <object>
        <name>head</name>
        <pose>Unspecified</pose>
        <truncated>0</truncated>
        <occluded>0</occluded>
        <difficult>0</difficult>
        <bndbox>
            <xmin>242</xmin>
            <ymin>154</ymin>
            <xmax>258</xmax>
            <ymax>171</ymax>
        </bndbox>
    </object>
    <object>
        <name>head</name>
        <pose>Unspecified</pose>
        <truncated>0</truncated>
        <occluded>0</occluded>
        <difficult>0</difficult>
        <bndbox>
            <xmin>276</xmin>
            <ymin>139</ymin>
            <xmax>295</xmax>
            <ymax>163</ymax>
        </bndbox>
    </object>
    <object>
        <name>head</name>
        <pose>Unspecified</pose>
        <truncated>0</truncated>
        <occluded>0</occluded>
        <difficult>0</difficult>
        <bndbox>
            <xmin>306</xmin>
            <ymin>151</ymin>
            <xmax>319</xmax>
            <ymax>169</ymax>
        </bndbox>
    </object>
    <object>
        <name>head</name>
        <pose>Unspecified</pose>
        <truncated>0</truncated>
        <occluded>0</occluded>
        <difficult>0</difficult>
        <bndbox>
            <xmin>55</xmin>
            <ymin>0</ymin>
            <xmax>85</xmax>
            <ymax>9</ymax>
        </bndbox>
    </object>
    <object>
        <name>head</name>
        <pose>Unspecified</pose>
        <truncated>0</truncated>
        <occluded>0</occluded>
        <difficult>0</difficult>
        <bndbox>
            <xmin>135</xmin>
            <ymin>0</ymin>
            <xmax>156</xmax>
            <ymax>8</ymax>
        </bndbox>
    </object>
</annotation>