
<annotation>
    <folder>images</folder>
    <filename>hard_hat_workers3528.png</filename>
    <size>
        <width>416</width>
        <height>416</height>
        <depth>3</depth>
    </size>
    <segmented>0</segmented>
    <object>
        <name>helmet</name>
        <pose>Unspecified</pose>
        <truncated>0</truncated>
        <occluded>0</occluded>
        <difficult>0</difficult>
        <bndbox>
            <xmin>215</xmin>
            <ymin>111</ymin>
            <xmax>289</xmax>
            <ymax>208</ymax>
        </bndbox>
    </object>
</annotation>