
<annotation>
    <folder>images</folder>
    <filename>hard_hat_workers2710.png</filename>
    <size>
        <width>415</width>
        <height>416</height>
        <depth>3</depth>
    </size>
    <segmented>0</segmented>
    <object>
        <name>helmet</name>
        <pose>Unspecified</pose>
        <truncated>0</truncated>
        <occluded>0</occluded>
        <difficult>0</difficult>
        <bndbox>
            <xmin>185</xmin>
            <ymin>210</ymin>
            <xmax>211</xmax>
            <ymax>228</ymax>
        </bndbox>
    </object>
    <object>
        <name>helmet</name>
        <pose>Unspecified</pose>
        <truncated>0</truncated>
        <occluded>0</occluded>
        <difficult>0</difficult>
        <bndbox>
            <xmin>282</xmin>
            <ymin>149</ymin>
            <xmax>302</xmax>
            <ymax>167</ymax>
        </bndbox>
    </object>
    <object>
        <name>helmet</name>
        <pose>Unspecified</pose>
        <truncated>0</truncated>
        <occluded>0</occluded>
        <difficult>0</difficult>
        <bndbox>
            <xmin>150</xmin>
            <ymin>208</ymin>
            <xmax>173</xmax>
            <ymax>227</ymax>
        </bndbox>
    </object>
</annotation>