
<annotation>
    <folder>images</folder>
    <filename>hard_hat_workers1486.png</filename>
    <size>
        <width>416</width>
        <height>416</height>
        <depth>3</depth>
    </size>
    <segmented>0</segmented>
    <object>
        <name>helmet</name>
        <pose>Unspecified</pose>
        <truncated>0</truncated>
        <occluded>0</occluded>
        <difficult>0</difficult>
        <bndbox>
            <xmin>39</xmin>
            <ymin>156</ymin>
            <xmax>76</xmax>
            <ymax>205</ymax>
        </bndbox>
    </object>
    <object>
        <name>helmet</name>
        <pose>Unspecified</pose>
        <truncated>0</truncated>
        <occluded>0</occluded>
        <difficult>0</difficult>
        <bndbox>
            <xmin>103</xmin>
            <ymin>151</ymin>
            <xmax>140</xmax>
            <ymax>201</ymax>
        </bndbox>
    </object>
    <object>
        <name>head</name>
        <pose>Unspecified</pose>
        <truncated>0</truncated>
        <occluded>0</occluded>
        <difficult>0</difficult>
        <bndbox>
            <xmin>21</xmin>
            <ymin>162</ymin>
            <xmax>44</xmax>
            <ymax>196</ymax>
        </bndbox>
    </object>
    <object>
        <name>head</name>
        <pose>Unspecified</pose>
        <truncated>0</truncated>
        <occluded>0</occluded>
        <difficult>0</difficult>
        <bndbox>
            <xmin>67</xmin>
            <ymin>166</ymin>
            <xmax>91</xmax>
            <ymax>201</ymax>
        </bndbox>
    </object>
    <object>
        <name>head</name>
        <pose>Unspecified</pose>
        <truncated>0</truncated>
        <occluded>0</occluded>
        <difficult>0</difficult>
        <bndbox>
            <xmin>149</xmin>
            <ymin>168</ymin>
            <xmax>176</xmax>
            <ymax>202</ymax>
        </bndbox>
    </object>
    <object>
        <name>head</name>
        <pose>Unspecified</pose>
        <truncated>0</truncated>
        <occluded>0</occluded>
        <difficult>0</difficult>
        <bndbox>
            <xmin>181</xmin>
            <ymin>169</ymin>
            <xmax>200</xmax>
            <ymax>198</ymax>
        </bndbox>
    </object>
    <object>
        <name>head</name>
        <pose>Unspecified</pose>
        <truncated>0</truncated>
        <occluded>0</occluded>
        <difficult>0</difficult>
        <bndbox>
            <xmin>195</xmin>
            <ymin>155</ymin>
            <xmax>229</xmax>
            <ymax>199</ymax>
        </bndbox>
    </object>
    <object>
        <name>head</name>
        <pose>Unspecified</pose>
        <truncated>0</truncated>
        <occluded>0</occluded>
        <difficult>0</difficult>
        <bndbox>
            <xmin>298</xmin>
            <ymin>166</ymin>
            <xmax>328</xmax>
            <ymax>205</ymax>
        </bndbox>
    </object>
    <object>
        <name>head</name>
        <pose>Unspecified</pose>
        <truncated>0</truncated>
        <occluded>0</occluded>
        <difficult>0</difficult>
        <bndbox>
            <xmin>330</xmin>
            <ymin>158</ymin>
            <xmax>373</xmax>
            <ymax>208</ymax>
        </bndbox>
    </object>
    <object>
        <name>head</name>
        <pose>Unspecified</pose>
        <truncated>0</truncated>
        <occluded>0</occluded>
        <difficult>0</difficult>
        <bndbox>
            <xmin>388</xmin>
            <ymin>160</ymin>
            <xmax>415</xmax>
            <ymax>202</ymax>
        </bndbox>
    </object>
</annotation>